esri2gpd/__init__.py
esri2gpd/core.py
esri2gpd/tests/__init__.py
esri2gpd/tests/test_get.py
esri2gpd-1.0.13.dist-info/LICENSE
esri2gpd-1.0.13.dist-info/WHEEL
esri2gpd-1.0.13.dist-info/METADATA
esri2gpd-1.0.13.dist-info/RECORD
